pyframes/__init__.py
pyframes/frames.py
pyframes-0.0.20.dist-info/METADATA
pyframes-0.0.20.dist-info/WHEEL
pyframes-0.0.20.dist-info/top_level.txt
pyframes-0.0.20.dist-info/RECORD
