Metadata-Version: 2.1
Name: pyframes
Version: 0.0.20
Summary: Python interface for the frames.ai database.
Home-page: https://github.com/Sensoritio/pyframes
Author: Darryn Anton Jordan
Author-email: <darryn@sensorit.io>
License: UNKNOWN
Keywords: python,frames.ai,sensorit
Platform: UNKNOWN
Classifier: Development Status :: 1 - Planning
Classifier: Intended Audience :: Developers
Classifier: Programming Language :: Python :: 3
Classifier: Operating System :: Unix
Classifier: Operating System :: MacOS :: MacOS X
Classifier: Operating System :: Microsoft :: Windows
Requires-Dist: numpy
Requires-Dist: pillow
Requires-Dist: requests
